{"Wed Feb 27 22:49:00 ": "Good night Techno world! http://t.co/yFRrA2BXyz", "Wed Apr 24 07:10:09 ": "Ho pubblicato una nuova foto su Facebook http://t.co/0NtiWwutb6", "Sat Mar 30 16:36:41 ": "BOOM!!!! http://t.co/mop5uUvaud", "Sat Mar 23 19:05:50 ": "Ho pubblicato una nuova foto su Facebook http://t.co/c1P3VeFdx2", "Sun Mar 10 06:02:21 ": "Ho pubblicato una nuova foto su Facebook http://t.co/hflH3B9l5t", "Tue Mar 05 08:23:38 ": "Ho pubblicato una nuova foto su Facebook http://t.co/aF4Pe0cT04", "Wed Apr 24 15:46:15 ": "Un peque\u00f1o regalo para usted!\na little present for you!\n6 entre mis temas cl\u00e1sicos GRATIS PARA DESCARGAR!\n6 of my... http://t.co/5e3W5B6h3C", "Mon Apr 22 21:41:52 ": "Good night Techno world! http://t.co/hpDbit1YL4", "Thu Feb 21 13:19:54 ": "Ho pubblicato una nuova foto su Facebook http://t.co/tDyyx5rda8", "Tue Feb 19 08:35:21 ": "15 FREE DOWNLOADS!!!!!\ngood morning facebook friends!!!! :)\nhere a present for you:\nsome of my original... http://t.co/PwLMGK01", "Thu Apr 18 13:52:43 ": "new track done:\nAnGy KoRe - With the cocaine CUT VERSION (only the track....) :)\ncheck it! http://t.co/1sZoHIaeVn", "Sun Mar 31 10:06:47 ": "Just arrived now in Landshut (Germnay),for play tonight in Buahaus club!\nhere a little present for you.... \na... http://t.co/W5w5lde9qh", "Thu Apr 04 23:08:16 ": "Keep calm and stay nervous...xD", "Sat Apr 20 14:53:54 ": "What a so great time I had yesterday in London! \nnice party,amazing people...funny!!!\nand now I'm in Montpellier,... http://t.co/xpj7Piudo6", "Thu Mar 07 11:34:09 ": "AnGy KoRe gigs update: \n(info booking:giorgio@youth-am.com) \n\n09.03.2013 ANGY KORE @ FabriQ [Glasgow - Scottland]... http://t.co/UUk2YV8KRk", "Mon Feb 18 17:15:04 ": "Ho pubblicato una nuova foto su Facebook http://t.co/cYsdSlww", "Mon Apr 01 05:28:27 ": "Ho pubblicato una nuova foto su Facebook http://t.co/yWayoxPxGZ", "Fri Mar 22 14:18:44 ": "Don't worry,\nbe TECHNO!", "Tue Mar 12 08:44:31 ": "good morning Techno ladies and gentlemen!\nI'm glad to introduce you a short preview of one of my next ep on... http://t.co/JeTiYr8Yhe", "Wed Feb 20 17:37:36 ": "still so hot!!!!\nREMAIN RECORDS (Axel Karakasis label)_ http://t.co/PLdp9IyV", "Tue Feb 19 08:33:14 ": "good morning facebook friends!!!! :)\nhere a present for you:\nsome of my original tracks/remixes (discography... http://t.co/9JpS7uDC", "Wed Mar 27 17:59:17 ": "yo!", "Thu Feb 28 15:14:01 ": "cant' wait for tomorrow!!!!\nABSTRACT night at Butan Club (official) with a massive line up!!!!\nand saturday I'll... http://t.co/SpgkRbARJN", "Tue Feb 26 23:08:08 ": "good night Techno friends! http://t.co/ceqCwwBeCy", "Tue Feb 19 08:34:19 ": "good morning facebook friends!!!! :)\nhere a present for you:\nsome of my original tracks/remixes (discography... http://t.co/haP6pIcz", "Fri Apr 12 07:08:32 ": "60000 THANX\n&lt;3", "Sat Feb 16 07:14:52 ": "Ho pubblicato una nuova foto su Facebook http://t.co/8N4Qr1o8", "Wed Feb 13 20:19:40 ": "Ho pubblicato una nuova foto su Facebook http://t.co/e6Ejdpmr", "Mon Apr 22 15:28:41 ": "Back home from an amazing weekend!\nI confirm again that Montpellier is one of my favorite french city!\nUnited 8... http://t.co/nDVW4EmNT2", "Mon Mar 04 19:41:31 ": "Ho pubblicato una nuova foto su Facebook http://t.co/Ep8MYYFQPO", "Sat Mar 30 15:57:44 ": "Ho pubblicato 2 foto su Facebook nell'album \"Flyers gigs AnGy KoRe\" http://t.co/zl0OjxNoAN", "Fri Mar 08 08:57:27 ": "Ho pubblicato una nuova foto su Facebook http://t.co/GxGpSKcn6I", "Mon Apr 08 12:37:51 ": "one week without use Facebook :)\nsometimes is good!", "Wed Mar 20 18:38:20 ": "Ho pubblicato una nuova foto su Facebook http://t.co/wFmHMJMGyH", "Sat Mar 02 16:44:57 ": "last night Butane club was massive!\nThanx 1000 Wuppertal &lt;3\nnow its time to have some rest...\nsee ya in a few... http://t.co/QzyegQSOHd", "Thu Feb 21 18:07:20 ": "BOOM!!!! http://t.co/RzcHZSuzoD", "Wed Apr 24 06:59:14 ": "Ho pubblicato 46 foto su Facebook nell'album \"AnGy KoRe @ Plan X (Kuala Lumpur,Malaysia) _ 04/05/2012!!!!\" http://t.co/Rm9nLkxPQC", "Wed Mar 06 20:02:49 ": "More wine for him! \nThanx ;) http://t.co/dGfgTHNj0k", "Fri Mar 08 17:12:44 ": "Ho pubblicato una nuova foto su Facebook http://t.co/38YytnWy0G", "Wed Mar 06 17:34:39 ": "More wine for him! ...pls ;) http://t.co/hGCXJNghiI", "Mon Mar 11 10:37:06 ": "RT @koengroeneveld: Still rockin things in the Beatport Minimal chart @Angy_KoRe \"Out Of My Way\" (Koen Groeneveld Remix) http://t.co/TUI ...", "Wed Apr 10 20:15:14 ": "MORE WINE FOR HIM_\nKombination Research (THE ADVENT label)_\nCheers! ;) http://t.co/OR3YEohfcB", "Wed Mar 06 17:33:53 ": "More wine for him....pls ;) http://t.co/Fn5PmO8wFa", "Fri Apr 19 11:52:43 ": "and I think this weekend will be so hot!!!!\nTonight I'll play @ Rhythm Factory [London - UK] FIRST TIME IN UK!!!!... http://t.co/r7ur0Ee9Rb", "Thu Apr 11 10:49:05 ": "Ho pubblicato una nuova foto su Facebook http://t.co/YnLBl9yjjP", "Thu Mar 14 09:49:53 ": "one day of holiday and I'm feeling born again....woow!\nNow studio time!!!", "Thu Mar 21 16:04:27 ": "SEX,DRUGS and TECHNO or\nPEACE,LOVE and TECHNO !!!!\nHow do you spend your TIME IN LIFE?\n:) http://t.co/SsLfVGWE1A", "Sat Mar 30 12:10:38 ": "GRAZIE ROMA &lt;3 http://t.co/MvX2OQw2VF", "Mon Feb 18 13:13:52 ": "Ho pubblicato una nuova foto su Facebook http://t.co/MwcpfhLx", "Fri Mar 29 07:40:03 ": "Ho pubblicato 61 foto su Facebook nell'album \"AnGy KoRe,Dandi&amp;Ugo,Niereich @ Butan (Wuppertal,Germany)_01/03/13\" http://t.co/cO8XOfGlix", "Mon Feb 11 17:34:21 ": "After 7 hours of delay finally my boarding to Lisbon xD\nSee ya Tonight at Faktory club!!!!", "Mon Feb 11 23:24:13 ": "Ho pubblicato una nuova foto su Facebook http://t.co/Vctr21kz", "Sat Mar 16 13:50:38 ": "Yesterday night Koln was awesome! &lt;3\nI want to say a big thanx for the amazing party in Art Teather.\nThe crowd was... http://t.co/pXVGVkE6dz", "Mon Apr 01 22:06:12 ": "Happy birthday to me :)", "Fri Feb 22 14:02:22 ": "Ho pubblicato 16 foto su Facebook nell'album \"AnGy KoRe @ Youtha-am showcase,Dual Beat (Naples) 08/\" http://t.co/IG8rvr2Enr", "Fri Mar 15 17:48:40 ": "back in Koln!!!!\nTonight I'll play for my third time in Art Teather club,and I'm  so excited like the first time... http://t.co/42MaerVGPB", "Thu Feb 14 19:07:04 ": "preparing my bag for tomorrow!\nI'm so happy to come back in Brno!\nse ya tomorrow at club 7.nebe! &lt;3\n\n(here a... http://t.co/Kfd2Hnzc", "Fri Mar 22 11:41:47 ": "Ho pubblicato una nuova foto su Facebook http://t.co/CBa43cagHI", "Thu Apr 11 14:58:17 ": "So far so....old... xD\nDo you remember it? :) http://t.co/pJ0lqgg2nZ", "Sat Apr 13 18:37:58 ": "I think tonight will be so hot!!!!\n:) http://t.co/JYIzd3MNRU", "Wed Feb 27 11:48:13 ": "Ho pubblicato una nuova foto su Facebook http://t.co/ZR84LHkt8i", "Sun Apr 14 14:01:38 ": "A bien tot Tolouse!\nMerci Mad Fest &lt;3", "Mon Apr 22 19:24:19 ": "Ho pubblicato 4 foto su Facebook nell'album \"Flyers gigs AnGy KoRe\" http://t.co/zvnuE3JhdG", "Mon Mar 18 23:18:36 ": "FUCK NORMALITY\nI am TECHNO !!!!", "Thu Feb 28 09:41:06 ": "Ho pubblicato una nuova foto su Facebook http://t.co/OEdRtp4N6e", "Tue Mar 05 07:21:39 ": "Ho pubblicato 2 foto su Facebook nell'album \"Flyers gigs AnGy KoRe\" http://t.co/kKN1TZdhQN", "Mon Mar 18 10:49:32 ": "Ho pubblicato una nuova foto su Facebook http://t.co/WUorBBQy5w", "Fri Mar 22 11:42:13 ": "Ho pubblicato una nuova foto su Facebook http://t.co/nnl5dOQ50g", "Tue Feb 26 11:26:07 ": "now on Beatport:\nAnGy KoRe - More wine for him ep_\nKombination Research! http://t.co/7dcpZFh26T", "Tue Apr 16 21:32:57 ": "TECHNO is....", "Wed Feb 20 14:36:08 ": "Hello Australian Friends! In November I'll be in Melbourne.... If anyone is interested on my Upcoming Shows... http://t.co/LXQCLqWB", "Tue Apr 23 11:27:23 ": "Ho pubblicato 19 foto su Facebook nell'album \"\" http://t.co/a2UDWGNWCv", "Thu Mar 14 20:56:31 ": "time to prepare my bag...\nsee ya tomorrow in art Teather club,Koln (Germany)\nI'm so happy to be back for my third... http://t.co/0ysAUG5fcO", "Tue Feb 26 17:51:01 ": "Ho pubblicato una nuova foto su Facebook http://t.co/qxfHx5BCxW", "Thu Feb 14 14:10:30 ": "Ho pubblicato una nuova foto su Facebook http://t.co/sq8xgoO5", "Sat Mar 02 17:12:47 ": "Ho pubblicato una nuova foto su Facebook http://t.co/JjKmcpXaon", "Sun Mar 03 18:51:19 ": "Friday night Butan Club (official) (Wuppertal),and saturday UG B\u00fclach,I had a very special weekend &lt;3\nbut now... http://t.co/HpwKPH0uxE", "Mon Mar 11 20:30:49 ": "Whop hop!!!!\nAnGy KoRe M\u00e9xico Tour 2013 Promo Video\nFalta pocoooo ;) http://t.co/UZkB0agDl1", "Tue Mar 05 19:53:04 ": "BOOM!\ncheck my upcoming release on ITALO BUSINESS!\nAnGy KoRe - REBEL\nIt includes massive remixes from\n A.Paul,... http://t.co/P1T4TUIKh0", "Wed Mar 06 10:43:24 ": "oh yeah!", "Wed Apr 24 07:14:45 ": "Ho pubblicato una nuova foto su Facebook http://t.co/VR1YtCUjA9", "Thu Feb 14 08:28:11 ": "Love is always bestowed as a gift - freely, willingly, and without expectation - We don't love to be loved; we... http://t.co/Qj5vKARm", "Wed Apr 17 17:47:57 ": "FAT REMIX!!!! http://t.co/iTlwVQUGjq", "Tue Mar 05 19:51:28 ": "BOOM!\ncheck my upcoming release on ITALO BUSINESS!\nAnGy KoRe - REBEL\nIt included massive remixes from... http://t.co/Y4Weearh3z", "Sat Mar 09 16:57:51 ": "in Glasgow! \nsee ya tonight FabrIQ Glasgow ;) http://t.co/rJxYbYmpQb", "Thu Mar 14 09:56:34 ": "Ho pubblicato una nuova foto su Facebook http://t.co/e1lYedwZiA", "Mon Apr 15 13:11:23 ": "START FORMAT IT_ http://t.co/EuBl3aWfBf", "Wed Mar 20 14:14:44 ": "A short video from last saturday in Art Teatche club (Koln,Germany)!\n\nTOTALLY CRAZY !!!!!\n\nsee you this... http://t.co/2DLRj5LEM2", "Wed Feb 13 23:08:11 ": "Out of my way_ http://t.co/gX3aIyGI", "Sun Feb 17 18:20:20 ": "Groove! http://t.co/8RTfv3CB", "Fri Feb 15 18:03:33 ": "TONIGHT IN BRNO (Czech republic)_ http://t.co/VZDIL7wQ", "Fri Apr 12 14:10:31 ": "reached 60000 likes on my Facebook Fan page,\nas I promised, \nhere for you in FREE DOWNLOAD my last \nBOOTLEG REMIX... http://t.co/zECCWygZLH", "Thu Apr 18 22:41:08 ": "Today I feel really satisfied! :)\nI completed 3 tracks and I already signed them on some massive labels! (info... http://t.co/PP4qCCGfP0", "Mon Apr 08 20:21:18 ": "FUKKIT_ http://t.co/5KQrIZ6lhC", "Tue Apr 23 07:37:05 ": "Ho pubblicato una nuova foto su Facebook http://t.co/o3LUjtNFhj", "Wed Feb 13 13:41:47 ": "Ho pubblicato una nuova foto su Facebook http://t.co/qjATCoYO", "Thu Feb 14 17:50:45 ": "coming soon on MASTER OF DISASTER_\nKlaudia Gawlas and Eric Sneo label_\nmore info soon!!! http://t.co/9LvGPorF", "Thu Feb 21 11:14:32 ": "I received an amazing remix of my track \"Point of View\" from the massive Techno Lady KLAUDIA GAWLAS!!!!\nBig... http://t.co/MRGxnJnu12", "Thu Mar 21 11:10:06 ": "BOOM!\ngood morning Techno friends!!!!\nhere 2 short previews of my second ep signed on 069Techno ( Alex Bau label... http://t.co/reQSggQm3s", "Tue Feb 26 17:59:25 ": "Ho pubblicato una nuova foto su Facebook http://t.co/UDGRH1uUeO"}